{
    "$schema": "http://json-schema.org/draft-04/schema#",
    "type": "object",
    "properties": {
      "displayID": {
        "type": "string"
      },
      "type": {
        "type": "string"
      },
      "expDate": {
        "type": "string"
      },
      "displayName": {
        "type": "string"
      },
      "storageURL": {
        "type": "string"
      },
      "ownerID": {
        "type": "string"
      },
      "createdDateTime": {
        "type": "string"
      },
      "createdByIP": {
        "type": "string"
      },
      "active": {
        "type": "boolean"
      }
    },
    "required": [
      "displayID",
      "type",
      "expDate",
      "displayName",
      "storageURL",
      "ownerID",
      "createdDateTime",
      "createdByIP",
      "active"
    ]
}